LICENSE
MANIFEST.in
README
setup.py
clpszawesome/__init__.py
clpszawesome.egg-info/PKG-INFO
clpszawesome.egg-info/SOURCES.txt
clpszawesome.egg-info/dependency_links.txt
clpszawesome.egg-info/top_level.txt