Metadata-Version: 1.0
Name: clpszawesome
Version: 0.1.0
Summary: first pypi
Home-page: https://github.com/clpsz
Author: Peter Zuo
Author-email: pengclpsz@gmail.com
License: LICENSE.txt
Platform: UNKNOWN
